cjrh_template.py
cjrh_template-2017.10.18.dist-info/LICENSE
cjrh_template-2017.10.18.dist-info/WHEEL
cjrh_template-2017.10.18.dist-info/METADATA
cjrh_template-2017.10.18.dist-info/RECORD
