Metadata-Version: 1.2
Name: cjrh_template
Version: 2017.10.18
Summary: Subclass for string.Template: adds placeholders() method. 
Home-page: https://github.com/cjrh/cjrh_template
License: UNKNOWN
Keywords: string.Template Template
Author: Caleb Hattingh
Author-email: caleb.hattingh@gmail.com
Classifier: Intended Audience :: Developers
Classifier: License :: OSI Approved :: Apache Software License
Classifier: Programming Language :: Python :: 2.7
Classifier: Programming Language :: Python :: 3.4
Classifier: Programming Language :: Python :: 3.5
Classifier: Programming Language :: Python :: 3.6
Classifier: Operating System :: OS Independent
Classifier: Topic :: Software Development :: Libraries :: Python Modules
